styledPrinting/__init__.py
styledPrinting-1.2.dist-info/METADATA
styledPrinting-1.2.dist-info/WHEEL
styledPrinting-1.2.dist-info/top_level.txt
styledPrinting-1.2.dist-info/RECORD
